curibio.sdk-0.18.1-py3.9-nspkg.pth
curibio/sdk/__init__.py
curibio/sdk/constants.py
curibio/sdk/excel_well_file.py
curibio/sdk/exceptions.py
curibio/sdk/jupyter_helpers.py
curibio/sdk/plate_recording.py
curibio/sdk/utils.py
curibio.sdk-0.18.1.dist-info/LICENSE
curibio.sdk-0.18.1.dist-info/METADATA
curibio.sdk-0.18.1.dist-info/WHEEL
curibio.sdk-0.18.1.dist-info/namespace_packages.txt
curibio.sdk-0.18.1.dist-info/top_level.txt
curibio.sdk-0.18.1.dist-info/RECORD
