Metadata-Version: 2.1
Name: curibio.sdk
Version: 0.18.1
Summary: CREATE A DESCRIPTION
Home-page: https://github.com/CuriBio/curibio.sdk
Author: Curi Bio
Author-email: contact@curibio.com
License: MIT
Project-URL: Documentation, https://curibiosdk.readthedocs.io/en/latest/
Platform: UNKNOWN
Classifier: Development Status :: 1 - Planning
Classifier: Intended Audience :: Science/Research
Classifier: License :: OSI Approved :: MIT License
Classifier: Programming Language :: Python
Classifier: Programming Language :: Python :: 3
Classifier: Programming Language :: Python :: 3.7
Classifier: Programming Language :: Python :: 3.8
Classifier: Programming Language :: Python :: 3.9
Classifier: Topic :: Scientific/Engineering
License-File: LICENSE
Requires-Dist: h5py (>=3.2.1)
Requires-Dist: nptyping (>=1.4.1)
Requires-Dist: numpy (>=1.20.1)
Requires-Dist: immutabledict (>=1.2.0)
Requires-Dist: XlsxWriter (>=1.3.8)
Requires-Dist: openpyxl (>=3.0.7)
Requires-Dist: matplotlib (>=3.4.1)
Requires-Dist: mantarray-file-manager (==0.5.1)
Requires-Dist: stdlib-utils (>=0.4.4)
Requires-Dist: mantarray-waveform-analysis (==1.1.1)
Requires-Dist: labware-domain-models (>=0.3.1)
Requires-Dist: requests (>=2.25.1)
Requires-Dist: importlib-metadata (>=3.7.3) ; python_version < "3.8"
